{
    "de3a7dd8-86f9-8652-fb65-9a8e5d8a73a0": {
        "paletteKey": "FlexLayoutCol",
        "commentid": null,
        "designerReference": [
            {
                "_key": "componentLabel",
                "_value": "Column",
                "_type": "kv",
                "_attrDef": "p",
                "_useAsLabel": true
            },
            {
                "_key": "style",
                "_value": "height: calc( 100vh - 56px );background-image: url('https://i.pinimg.com/564x/8c/98/99/8c98994518b575bfd8c949e91d20548b.jpg')",
                "_type": "kv",
                "_attrDef": "p"
            },
            {
                "_key": "class",
                "_value": [
                    "chat-container"
                ],
                "_type": "dav",
                "_attrDef": "p"
            },
            {
                "_key": "fxFlex",
                "_value": "",
                "_type": "kv",
                "_attrDef": "p"
            },
            {
                "_key": "fxLayoutGap",
                "_value": "",
                "_type": "kv",
                "_attrDef": "p"
            },
            {
                "_key": "wrap",
                "_value": "",
                "_type": "a",
                "_attrDef": "p"
            },
            {
                "_key": "layoutAlign",
                "_value": "start",
                "_type": "a",
                "_attrDef": "p"
            },
            {
                "_key": "pLayoutAlign",
                "_value": "stretch",
                "_type": "a",
                "_attrDef": "p"
            },
            {
                "_key": "[fxShow]",
                "_value": "true",
                "_type": "kv",
                "_attrDef": "p"
            }
        ],
        "f6ec44e4-43b5-a592-ad7a-5ca53a427e71": {
            "paletteKey": "FlexLayoutRow",
            "parentEditorKey": "de3a7dd8-86f9-8652-fb65-9a8e5d8a73a0",
            "commentid": null,
            "designerReference": [
                {
                    "_key": "componentLabel",
                    "_value": "Row",
                    "_type": "kv",
                    "_attrDef": "p",
                    "_useAsLabel": true
                },
                {
                    "_key": "style",
                    "_value": "height:50px;padding:10px;",
                    "_type": "kv",
                    "_attrDef": "p"
                },
                {
                    "_key": "class",
                    "_value": [
                        "accent-color"
                    ],
                    "_type": "dav",
                    "_attrDef": "p"
                },
                {
                    "_key": "fxFlex",
                    "_value": "",
                    "_type": "kv",
                    "_attrDef": "p"
                },
                {
                    "_key": "fxLayoutGap",
                    "_value": "1em",
                    "_type": "kv",
                    "_attrDef": "p"
                },
                {
                    "_key": "wrap",
                    "_value": "wrap",
                    "_type": "a",
                    "_attrDef": "p"
                },
                {
                    "_key": "layoutAlign",
                    "_value": "start",
                    "_type": "a",
                    "_attrDef": "p"
                },
                {
                    "_key": "pLayoutAlign",
                    "_value": "center",
                    "_type": "a",
                    "_attrDef": "p"
                },
                {
                    "_key": "[fxShow]",
                    "_value": "true",
                    "_type": "kv",
                    "_attrDef": "p"
                }
            ],
            "cab6328c-8668-e3b0-2fbf-14f1a60920c7": {
                "paletteKey": "NG-icon",
                "parentEditorKey": "f6ec44e4-43b5-a592-ad7a-5ca53a427e71",
                "commentid": null,
                "designerReference": [
                    {
                        "_key": "style",
                        "_value": "cursor:pointer;",
                        "_type": "kv",
                        "_attrDef": "p"
                    },
                    {
                        "_key": "class",
                        "_value": "",
                        "_type": "dav",
                        "_attrDef": "p"
                    },
                    {
                        "_key": "IconName",
                        "_value": "keyboard_arrow_left",
                        "_type": "a",
                        "_attrDef": "p",
                        "_useAsLabel": true
                    },
                    {
                        "_key": "[inline]",
                        "_value": "",
                        "_type": "kv",
                        "_attrDef": "p"
                    },
                    {
                        "_key": "color",
                        "_value": "",
                        "_type": "kv",
                        "_attrDef": "p"
                    },
                    {
                        "_key": "(click)",
                        "_value": "toGoBack()",
                        "_type": "kv",
                        "_attrDef": "c",
                        "objValue": {
                            "nodeID": "sd_l0ge4wGAqHKqH7uu",
                            "functionName": "toGoBack",
                            "activeTree": "pages",
                            "z": "sd_Cr7G5phrw9t1BQMQ",
                            "input": []
                        }
                    }
                ]
            },
            "e4e993db-2e69-913e-d8c7-9e81e00fa531": {
                "paletteKey": "NG-icon",
                "parentEditorKey": "f6ec44e4-43b5-a592-ad7a-5ca53a427e71",
                "commentid": null,
                "designerReference": [
                    {
                        "_key": "style",
                        "_value": "font-size:30px",
                        "_type": "kv",
                        "_attrDef": "p"
                    },
                    {
                        "_key": "class",
                        "_value": "",
                        "_type": "dav",
                        "_attrDef": "p"
                    },
                    {
                        "_key": "IconName",
                        "_value": "account_circle",
                        "_type": "a",
                        "_attrDef": "p",
                        "_useAsLabel": true
                    },
                    {
                        "_key": "[inline]",
                        "_value": "",
                        "_type": "kv",
                        "_attrDef": "p"
                    },
                    {
                        "_key": "color",
                        "_value": "",
                        "_type": "kv",
                        "_attrDef": "p"
                    }
                ]
            },
            "4439f2f8-20ae-aa16-ce16-ac6098780bbf": {
                "paletteKey": "Html5",
                "parentEditorKey": "f6ec44e4-43b5-a592-ad7a-5ca53a427e71",
                "isAdvancedComponent": true,
                "commentid": null,
                "designerReference": [
                    {
                        "_key": "style",
                        "_value": "color: black;",
                        "_type": "kv",
                        "_attrDef": "p"
                    },
                    {
                        "_key": "class",
                        "_value": [],
                        "_type": "dav",
                        "_attrDef": "p"
                    },
                    {
                        "_key": "htmlElement",
                        "_value": "div",
                        "_type": "dav",
                        "_attrDef": "p",
                        "_useAsLabel": true
                    },
                    {
                        "_key": "tagType",
                        "_value": "",
                        "_type": "a",
                        "_attrDef": "p",
                        "_visibility": false
                    },
                    {
                        "_key": "name",
                        "_value": "",
                        "_type": "kv",
                        "_attrDef": "p",
                        "_visibility": false
                    },
                    {
                        "_key": "sandbox",
                        "_value": "",
                        "_type": "kv",
                        "_attrDef": "p",
                        "_visibility": false
                    },
                    {
                        "_key": "src",
                        "_value": "",
                        "_type": "kv",
                        "_attrDef": "p",
                        "_visibility": false
                    },
                    {
                        "_key": "srcdoc",
                        "_value": "",
                        "_type": "kv",
                        "_attrDef": "p",
                        "_visibility": false
                    },
                    {
                        "_key": "width",
                        "_value": "",
                        "_type": "kv",
                        "_attrDef": "p",
                        "_visibility": false
                    },
                    {
                        "_key": "[autoplay]",
                        "_value": "",
                        "_type": "kv",
                        "_attrDef": "p",
                        "_visibility": false
                    },
                    {
                        "_key": "[loop]",
                        "_value": "",
                        "_type": "kv",
                        "_attrDef": "p",
                        "_visibility": false
                    },
                    {
                        "_key": "data",
                        "_value": "",
                        "_type": "kv",
                        "_attrDef": "p",
                        "_visibility": false
                    },
                    {
                        "_key": "audioSource",
                        "_value": [],
                        "_type": "a",
                        "_attrDef": "p",
                        "_visibility": false
                    },
                    {
                        "_key": "videoSource",
                        "_value": [],
                        "_type": "a",
                        "_attrDef": "p",
                        "_visibility": false
                    },
                    {
                        "_key": "audioDatasource",
                        "_value": "",
                        "_type": "a",
                        "_attrDef": "p",
                        "_visibility": false
                    },
                    {
                        "_key": "audioSrc",
                        "_value": "",
                        "_type": "a",
                        "_attrDef": "p",
                        "_visibility": false
                    },
                    {
                        "_key": "audioType",
                        "_value": "",
                        "_type": "a",
                        "_attrDef": "p",
                        "_visibility": false
                    },
                    {
                        "_key": "videoDatasource",
                        "_value": "",
                        "_type": "a",
                        "_attrDef": "p",
                        "_visibility": false
                    },
                    {
                        "_key": "videoSrc",
                        "_value": "",
                        "_type": "a",
                        "_attrDef": "p",
                        "_visibility": false
                    },
                    {
                        "_key": "videoType",
                        "_value": "",
                        "_type": "a",
                        "_attrDef": "p",
                        "_visibility": false
                    },
                    {
                        "_key": "(audioplay)",
                        "_value": "",
                        "_type": "a",
                        "_attrDef": "p",
                        "_visibility": false
                    },
                    {
                        "_key": "(videoplay)",
                        "_value": "",
                        "_type": "a",
                        "_attrDef": "p",
                        "_visibility": false
                    },
                    {
                        "_key": "(audiopause)",
                        "_value": "",
                        "_type": "kv",
                        "_attrDef": "p",
                        "_visibility": false
                    },
                    {
                        "_key": "(videopause)",
                        "_value": "",
                        "_type": "kv",
                        "_attrDef": "p",
                        "_visibility": false
                    },
                    {
                        "_key": "(audioended)",
                        "_value": "",
                        "_type": "kv",
                        "_attrDef": "p",
                        "_visibility": false
                    },
                    {
                        "_key": "(videoended)",
                        "_value": "",
                        "_type": "kv",
                        "_attrDef": "p",
                        "_visibility": false
                    }
                ],
                "c10c41d0-0b37-3bc0-e10f-1048130484f6": {
                    "paletteKey": "html-editor",
                    "parentEditorKey": "4439f2f8-20ae-aa16-ce16-ac6098780bbf",
                    "isAdvancedChildComponent": true,
                    "commentid": null,
                    "designerReference": [
                        {
                            "_key": "style",
                            "_value": "",
                            "_type": "kv",
                            "_attrDef": "p"
                        },
                        {
                            "_key": "class",
                            "_value": "",
                            "_type": "dav",
                            "_attrDef": "p"
                        },
                        {
                            "_key": "html",
                            "_value": "{{email}}",
                            "_type": "a",
                            "_attrDef": "p"
                        }
                    ]
                }
            }
        },
        "9d372289-f8c2-6060-2ea8-9c6c0e9c422e": {
            "paletteKey": "NEUTRINOS_VIEW_messages",
            "parentEditorKey": "de3a7dd8-86f9-8652-fb65-9a8e5d8a73a0",
            "commentid": null,
            "designerReference": [
                {
                    "_key": "componentLabel",
                    "_value": "messages",
                    "_type": "kv",
                    "_attrDef": "p",
                    "_useAsLabel": true
                },
                {
                    "_key": "style",
                    "_value": "flex:2; overflow:auto;",
                    "_type": "kv",
                    "_attrDef": "p"
                },
                {
                    "_key": "class",
                    "_value": "",
                    "_type": "dav",
                    "_attrDef": "p"
                },
                {
                    "_key": "(changeEvent)",
                    "_value": "",
                    "_type": "kv",
                    "_attrDef": "p",
                    "_complexity": "advanced",
                    "displayAs": "changeEvent",
                    "attrType": "OUTPUT",
                    "_customAttributeFlag": "flowpicker",
                    "inValid": false,
                    "message": ""
                },
                {
                    "_key": "[messages]",
                    "_value": "this.messages",
                    "_type": "kv",
                    "_attrDef": "p",
                    "_complexity": "advanced",
                    "displayAs": "messages",
                    "attrType": "INPUT",
                    "inValid": false,
                    "message": ""
                },
                {
                    "_key": "[currentUser]",
                    "_value": "this.currentUser",
                    "_type": "kv",
                    "_attrDef": "p",
                    "_complexity": "advanced",
                    "displayAs": "currentUser",
                    "attrType": "INPUT",
                    "inValid": false,
                    "message": ""
                },
                {
                    "_key": "[user]",
                    "_value": "",
                    "_type": "kv",
                    "_attrDef": "p",
                    "_complexity": "advanced",
                    "displayAs": "user",
                    "attrType": "INPUT",
                    "inValid": false,
                    "message": ""
                }
            ]
        },
        "677f1645-ce84-b6cc-034d-ea2c06a972a6": {
            "paletteKey": "FlexLayoutRow",
            "parentEditorKey": "de3a7dd8-86f9-8652-fb65-9a8e5d8a73a0",
            "commentid": null,
            "designerReference": [
                {
                    "_key": "componentLabel",
                    "_value": "Row",
                    "_type": "kv",
                    "_attrDef": "p",
                    "_useAsLabel": true
                },
                {
                    "_key": "style",
                    "_value": "background-color:whitesmoke;padding:10px;",
                    "_type": "kv",
                    "_attrDef": "p"
                },
                {
                    "_key": "class",
                    "_value": [],
                    "_type": "dav",
                    "_attrDef": "p"
                },
                {
                    "_key": "fxFlex",
                    "_value": "",
                    "_type": "kv",
                    "_attrDef": "p"
                },
                {
                    "_key": "fxLayoutGap",
                    "_value": "1em",
                    "_type": "kv",
                    "_attrDef": "p"
                },
                {
                    "_key": "wrap",
                    "_value": "wrap",
                    "_type": "a",
                    "_attrDef": "p"
                },
                {
                    "_key": "layoutAlign",
                    "_value": "start",
                    "_type": "a",
                    "_attrDef": "p"
                },
                {
                    "_key": "pLayoutAlign",
                    "_value": "center",
                    "_type": "a",
                    "_attrDef": "p"
                },
                {
                    "_key": "[fxShow]",
                    "_value": "true",
                    "_type": "kv",
                    "_attrDef": "p"
                }
            ],
            "95bce44b-c517-cf53-3b71-1657175ced06": {
                "paletteKey": "Html5",
                "parentEditorKey": "677f1645-ce84-b6cc-034d-ea2c06a972a6",
                "isAdvancedComponent": true,
                "commentid": null,
                "designerReference": [
                    {
                        "_key": "style",
                        "_value": "width: calc( 100% - 25px - 4em );border: none;     height: 15px;border-radius: 20px;outline: none;font-size: large;",
                        "_type": "kv",
                        "_attrDef": "p"
                    },
                    {
                        "_key": "class",
                        "_value": [
                            "padding-1"
                        ],
                        "_type": "dav",
                        "_attrDef": "p"
                    },
                    {
                        "_key": "htmlElement",
                        "_value": "input",
                        "_type": "dav",
                        "_attrDef": "p",
                        "_useAsLabel": true,
                        "_customAttributeFlag": "customInput"
                    },
                    {
                        "_key": "tagType",
                        "_value": "input",
                        "_type": "a",
                        "_attrDef": "p",
                        "_visibility": false
                    },
                    {
                        "_key": "name",
                        "_value": "",
                        "_type": "kv",
                        "_attrDef": "p",
                        "_visibility": false
                    },
                    {
                        "_key": "sandbox",
                        "_value": "",
                        "_type": "kv",
                        "_attrDef": "p",
                        "_visibility": false
                    },
                    {
                        "_key": "src",
                        "_value": "",
                        "_type": "kv",
                        "_attrDef": "p",
                        "_visibility": false
                    },
                    {
                        "_key": "srcdoc",
                        "_value": "",
                        "_type": "kv",
                        "_attrDef": "p",
                        "_visibility": false
                    },
                    {
                        "_key": "width",
                        "_value": "",
                        "_type": "kv",
                        "_attrDef": "p",
                        "_visibility": false
                    },
                    {
                        "_key": "[autoplay]",
                        "_value": "",
                        "_type": "kv",
                        "_attrDef": "p",
                        "_visibility": false
                    },
                    {
                        "_key": "[loop]",
                        "_value": "",
                        "_type": "kv",
                        "_attrDef": "p",
                        "_visibility": false
                    },
                    {
                        "_key": "data",
                        "_value": "",
                        "_type": "kv",
                        "_attrDef": "p",
                        "_visibility": false
                    },
                    {
                        "_key": "audioSource",
                        "_value": [],
                        "_type": "a",
                        "_attrDef": "p",
                        "_visibility": false
                    },
                    {
                        "_key": "videoSource",
                        "_value": [],
                        "_type": "a",
                        "_attrDef": "p",
                        "_visibility": false
                    },
                    {
                        "_key": "audioDatasource",
                        "_value": "",
                        "_type": "a",
                        "_attrDef": "p",
                        "_visibility": false
                    },
                    {
                        "_key": "audioSrc",
                        "_value": "",
                        "_type": "a",
                        "_attrDef": "p",
                        "_visibility": false
                    },
                    {
                        "_key": "audioType",
                        "_value": "",
                        "_type": "a",
                        "_attrDef": "p",
                        "_visibility": false
                    },
                    {
                        "_key": "videoDatasource",
                        "_value": "",
                        "_type": "a",
                        "_attrDef": "p",
                        "_visibility": false
                    },
                    {
                        "_key": "videoSrc",
                        "_value": "",
                        "_type": "a",
                        "_attrDef": "p",
                        "_visibility": false
                    },
                    {
                        "_key": "videoType",
                        "_value": "",
                        "_type": "a",
                        "_attrDef": "p",
                        "_visibility": false
                    },
                    {
                        "_key": "(audioplay)",
                        "_value": "",
                        "_type": "a",
                        "_attrDef": "p",
                        "_visibility": false
                    },
                    {
                        "_key": "(videoplay)",
                        "_value": "",
                        "_type": "a",
                        "_attrDef": "p",
                        "_visibility": false
                    },
                    {
                        "_key": "(audiopause)",
                        "_value": "",
                        "_type": "kv",
                        "_attrDef": "p",
                        "_visibility": false
                    },
                    {
                        "_key": "(videopause)",
                        "_value": "",
                        "_type": "kv",
                        "_attrDef": "p",
                        "_visibility": false
                    },
                    {
                        "_key": "(audioended)",
                        "_value": "",
                        "_type": "kv",
                        "_attrDef": "p",
                        "_visibility": false
                    },
                    {
                        "_key": "(videoended)",
                        "_value": "",
                        "_type": "kv",
                        "_attrDef": "p",
                        "_visibility": false
                    },
                    {
                        "_key": "[(ngModel)]",
                        "_value": "page.msg",
                        "_type": "kv",
                        "_attrDef": "c"
                    },
                    {
                        "_key": "(keyup.enter)",
                        "_value": "messsage()",
                        "_type": "kv",
                        "_attrDef": "c",
                        "_customAttributeFlag": "flowpicker",
                        "objValue": {
                            "nodeID": "sd_OBqG0WKQjed87EY5",
                            "functionName": "messsage",
                            "activeTree": "pages",
                            "z": "sd_Cr7G5phrw9t1BQMQ",
                            "input": []
                        }
                    },
                    {
                        "_key": "(input)",
                        "_value": "getTyping()",
                        "_type": "kv",
                        "_attrDef": "c",
                        "_customAttributeFlag": "flowpicker",
                        "objValue": {
                            "nodeID": "sd_W8wUIJWLiNvCwnHm",
                            "functionName": "getTyping",
                            "activeTree": "pages",
                            "z": "sd_Cr7G5phrw9t1BQMQ",
                            "input": []
                        }
                    }
                ]
            },
            "47fe1aa0-ec6d-3051-8698-b320521cfa93": {
                "paletteKey": "NG-icon",
                "parentEditorKey": "677f1645-ce84-b6cc-034d-ea2c06a972a6",
                "commentid": null,
                "designerReference": [
                    {
                        "_key": "style",
                        "_value": "cursor:pointer;",
                        "_type": "kv",
                        "_attrDef": "p"
                    },
                    {
                        "_key": "class",
                        "_value": "",
                        "_type": "dav",
                        "_attrDef": "p"
                    },
                    {
                        "_key": "IconName",
                        "_value": "send",
                        "_type": "a",
                        "_attrDef": "p",
                        "_useAsLabel": true
                    },
                    {
                        "_key": "[inline]",
                        "_value": "",
                        "_type": "kv",
                        "_attrDef": "p"
                    },
                    {
                        "_key": "color",
                        "_value": "",
                        "_type": "kv",
                        "_attrDef": "p"
                    },
                    {
                        "_key": "(click)",
                        "_value": "messsage()",
                        "_type": "kv",
                        "_attrDef": "c",
                        "objValue": {
                            "nodeID": "sd_OBqG0WKQjed87EY5",
                            "functionName": "messsage",
                            "activeTree": "pages",
                            "z": "sd_Cr7G5phrw9t1BQMQ",
                            "input": []
                        }
                    },
                    {
                        "_key": "*ngIf",
                        "_value": "page.isTyping",
                        "_type": "kv",
                        "_attrDef": "c"
                    }
                ]
            },
            "baf261ba-98de-1ba8-0066-0679a9b2edbd": {
                "paletteKey": "NG-icon",
                "parentEditorKey": "677f1645-ce84-b6cc-034d-ea2c06a972a6",
                "commentid": null,
                "designerReference": [
                    {
                        "_key": "style",
                        "_value": "",
                        "_type": "kv",
                        "_attrDef": "p"
                    },
                    {
                        "_key": "class",
                        "_value": [
                            "cursor"
                        ],
                        "_type": "dav",
                        "_attrDef": "p"
                    },
                    {
                        "_key": "IconName",
                        "_value": "settings_voice",
                        "_type": "a",
                        "_attrDef": "p",
                        "_useAsLabel": true
                    },
                    {
                        "_key": "[inline]",
                        "_value": "",
                        "_type": "kv",
                        "_attrDef": "p"
                    },
                    {
                        "_key": "color",
                        "_value": "",
                        "_type": "kv",
                        "_attrDef": "p"
                    },
                    {
                        "_key": "*ngIf",
                        "_value": "page.isRecording",
                        "_type": "kv",
                        "_attrDef": "c"
                    },
                    {
                        "_key": "(click)",
                        "_value": "startRecording()",
                        "_type": "kv",
                        "_attrDef": "c",
                        "objValue": {
                            "nodeID": "sd_3d5ZuDpqBUuYXpLg",
                            "functionName": "startRecording",
                            "activeTree": "pages",
                            "z": "sd_Cr7G5phrw9t1BQMQ",
                            "input": []
                        }
                    }
                ]
            }
        }
    }
}
